README.md
setup.cfg
setup.py
report/__init__.py
report/report.py
report_hub_cli.egg-info/PKG-INFO
report_hub_cli.egg-info/SOURCES.txt
report_hub_cli.egg-info/dependency_links.txt
report_hub_cli.egg-info/entry_points.txt
report_hub_cli.egg-info/requires.txt
report_hub_cli.egg-info/top_level.txt