Metadata-Version: 2.1
Name: report-hub-cli
Version: 0.0.3
Summary: Cli for ReportHub server
Home-page: https://github.com/grib9544/report-hub-cli
Author: grib9544
Author-email: grib9544@gmail.com
License: UNKNOWN
Project-URL: Bug Reports, https://github.com/grib9544/report-hub-cli/issues
Project-URL: Source, https://github.com/grib9544/report-hub-cli/
Platform: UNKNOWN
Classifier: Development Status :: 3 - Alpha
Classifier: Intended Audience :: Developers
Classifier: Topic :: Software Development :: Bug Tracking
Classifier: License :: OSI Approved :: MIT License
Classifier: Programming Language :: Python :: 3.4
Classifier: Programming Language :: Python :: 3.5
Classifier: Programming Language :: Python :: 3.6
Classifier: Programming Language :: Python :: 3.7
Classifier: Programming Language :: Python :: 3.8
Requires-Python: >=3.4
